{
  "fallback": "minecraft:empty",
  "elements": [
    {
      "weight": 1,
      "element": {
        "element_type": "minecraft:single_pool_element",
        "location": "dimensionmod:obsidian_column/s0_4",
        "projection": "rigid",
        "processors": "minecraft:empty"
      }
    },
    {
      "weight": 1,
      "element": {
        "element_type": "minecraft:single_pool_element",
        "location": "dimensionmod:obsidian_column/s0_8",
        "projection": "rigid",
        "processors": "minecraft:empty"
      }
    },
    {
      "weight": 1,
      "element": {
        "element_type": "minecraft:single_pool_element",
        "location": "dimensionmod:obsidian_column/s1_4",
        "projection": "rigid",
        "processors": "minecraft:empty"
      }
    },
    {
      "weight": 1,
      "element": {
        "element_type": "minecraft:single_pool_element",
        "location": "dimensionmod:obsidian_column/s1_8",
        "projection": "rigid",
        "processors": "minecraft:empty"
      }
    },
    {
      "weight": 1,
      "element": {
        "element_type": "minecraft:single_pool_element",
        "location": "dimensionmod:obsidian_column/s2_4",
        "projection": "rigid",
        "processors": "minecraft:empty"
      }
    },
    {
      "weight": 1,
      "element": {
        "element_type": "minecraft:single_pool_element",
        "location": "dimensionmod:obsidian_column/s2_8",
        "projection": "rigid",
        "processors": "minecraft:empty"
      }
    },
    {
      "weight": 1,
      "element": {
        "element_type": "minecraft:single_pool_element",
        "location": "dimensionmod:obsidian_column/s3_4",
        "projection": "rigid",
        "processors": "minecraft:empty"
      }
    },
    {
      "weight": 1,
      "element": {
        "element_type": "minecraft:single_pool_element",
        "location": "dimensionmod:obsidian_column/s3_8",
        "projection": "rigid",
        "processors": "minecraft:empty"
      }
    },
    {
      "weight": 1,
      "element": {
        "element_type": "minecraft:single_pool_element",
        "location": "dimensionmod:obsidian_column/s4_4",
        "projection": "rigid",
        "processors": "minecraft:empty"
      }
    },
    {
      "weight": 1,
      "element": {
        "element_type": "minecraft:single_pool_element",
        "location": "dimensionmod:obsidian_column/s4_8",
        "projection": "rigid",
        "processors": "minecraft:empty"
      }
    },
    {
      "weight": 1,
      "element": {
        "element_type": "minecraft:single_pool_element",
        "location": "dimensionmod:obsidian_column/s5_4",
        "projection": "rigid",
        "processors": "minecraft:empty"
      }
    },
    {
      "weight": 1,
      "element": {
        "element_type": "minecraft:single_pool_element",
        "location": "dimensionmod:obsidian_column/s5_8",
        "projection": "rigid",
        "processors": "minecraft:empty"
      }
    }
  ]
}